MANIFEST.in
README.txt
setup.cfg
setup.py
docs/HISTORY.txt
docs/INSTALL.txt
docs/LICENSE.GPL
docs/LICENSE.txt
plonetheme/__init__.py
plonetheme.sait2009.egg-info/PKG-INFO
plonetheme.sait2009.egg-info/SOURCES.txt
plonetheme.sait2009.egg-info/dependency_links.txt
plonetheme.sait2009.egg-info/entry_points.txt
plonetheme.sait2009.egg-info/namespace_packages.txt
plonetheme.sait2009.egg-info/not-zip-safe
plonetheme.sait2009.egg-info/requires.txt
plonetheme.sait2009.egg-info/top_level.txt
plonetheme/sait2009/.DS_Store
plonetheme/sait2009/__init__.py
plonetheme/sait2009/configure.zcml
plonetheme/sait2009/profiles.zcml
plonetheme/sait2009/setuphandlers.py
plonetheme/sait2009/skins.zcml
plonetheme/sait2009/tests.py
plonetheme/sait2009/version.txt
plonetheme/sait2009/browser/.DS_Store
plonetheme/sait2009/browser/__init__.py
plonetheme/sait2009/browser/configure.zcml
plonetheme/sait2009/browser/footer.pt
plonetheme/sait2009/browser/interfaces.py
plonetheme/sait2009/browser/logo.pt
plonetheme/sait2009/browser/sections.pt
plonetheme/sait2009/browser/viewlet.pt
plonetheme/sait2009/browser/viewlets.py
plonetheme/sait2009/browser/images/.DS_Store
plonetheme/sait2009/browser/images/README.txt
plonetheme/sait2009/browser/stylesheets/README.txt
plonetheme/sait2009/browser/stylesheets/main.css
plonetheme/sait2009/locales/.DS_Store
plonetheme/sait2009/locales/sait.pot
plonetheme/sait2009/locales/en/.DS_Store
plonetheme/sait2009/locales/en/LC_MESSAGES/.DS_Store
plonetheme/sait2009/locales/en/LC_MESSAGES/sait.mo
plonetheme/sait2009/locales/en/LC_MESSAGES/sait.po
plonetheme/sait2009/locales/ru/LC_MESSAGES/.DS_Store
plonetheme/sait2009/locales/ru/LC_MESSAGES/sait.mo
plonetheme/sait2009/locales/ru/LC_MESSAGES/sait.po
plonetheme/sait2009/locales/uk/LC_MESSAGES/.DS_Store
plonetheme/sait2009/locales/uk/LC_MESSAGES/sait.mo
plonetheme/sait2009/locales/uk/LC_MESSAGES/sait.po
plonetheme/sait2009/profiles/default/cssregistry.xml
plonetheme/sait2009/profiles/default/import_steps.xml
plonetheme/sait2009/profiles/default/jsregistry.xml
plonetheme/sait2009/profiles/default/metadata.xml
plonetheme/sait2009/profiles/default/plonetheme.sait2009_various.txt
plonetheme/sait2009/profiles/default/skins.xml
plonetheme/sait2009/profiles/default/viewlets.xml
plonetheme/sait2009/skins/.DS_Store
