Metadata-Version: 1.0
Name: plonetheme.sait2009
Version: 1.2
Summary: SAIT-2009 installable Plone theme
Home-page: http://sait.org.ua
Author: makukha
Author-email: m.makukha@gmail.com
License: GPL
Keywords: web zope plone theme sait 2009
Platform: UNKNOWN
Classifier: Framework :: Plone
Classifier: Programming Language :: Python
Classifier: Topic :: Software Development :: Libraries :: Python Modules
